[
	{
		"Compression": "zip",
		"Quality": 5,
		"Size": "01MB",
		"Type": "JPG",
		"EndTime": "2017-12-07T06:02:46.486293-02:00",
		"CompressedSize": "1031989",
		"BeginTime": "2017-12-07T06:02:44.997715-02:00",
		"FullSize": "1033414"
	},
	{
		"Compression": "zip",
		"Quality": 11,
		"Size": "01MB",
		"Type": "JPG",
		"EndTime": "2017-12-07T06:02:48.6909448-02:00",
		"CompressedSize": "1031989",
		"BeginTime": "2017-12-07T06:02:47.4000313-02:00",
		"FullSize": "1033414"
	},
	{
		"Compression": "tgz",
		"Quality": 5,
		"Size": "01MB",
		"Type": "JPG",
		"EndTime": "2017-12-07T06:02:51.4518582-02:00",
		"CompressedSize": "1032403",
		"BeginTime": "2017-12-07T06:02:49.547828-02:00",
		"FullSize": "1033414"
	},
	{
		"Compression": "tgz",
		"Quality": 11,
		"Size": "01MB",
		"Type": "JPG",
		"EndTime": "2017-12-07T06:02:54.4500627-02:00",
		"CompressedSize": "1032404",
		"BeginTime": "2017-12-07T06:02:52.790576-02:00",
		"FullSize": "1033414"
	},
	{
		"Compression": "zip",
		"Quality": 5,
		"Size": "30MB",
		"Type": "JPG",
		"EndTime": "2017-12-07T06:03:01.1368692-02:00",
		"CompressedSize": "30672912",
		"BeginTime": "2017-12-07T06:02:55.9065641-02:00",
		"FullSize": "30789588"
	},
	{
		"Compression": "zip",
		"Quality": 11,
		"Size": "30MB",
		"Type": "JPG",
		"EndTime": "2017-12-07T06:03:05.8959587-02:00",
		"CompressedSize": "30672912",
		"BeginTime": "2017-12-07T06:03:02.2495637-02:00",
		"FullSize": "30789588"
	},
	{
		"Compression": "tgz",
		"Quality": 5,
		"Size": "30MB",
		"Type": "JPG",
		"EndTime": "2017-12-07T06:03:10.2183853-02:00",
		"CompressedSize": "30705922",
		"BeginTime": "2017-12-07T06:03:06.8297065-02:00",
		"FullSize": "30789588"
	},
	{
		"Compression": "tgz",
		"Quality": 11,
		"Size": "30MB",
		"Type": "JPG",
		"EndTime": "2017-12-07T06:03:14.6540843-02:00",
		"CompressedSize": "30705919",
		"BeginTime": "2017-12-07T06:03:11.2361797-02:00",
		"FullSize": "30789588"
	},
	{
		"Compression": "zip",
		"Quality": 5,
		"Size": "01MB",
		"Type": "MP3",
		"EndTime": "2017-12-07T06:03:16.9501196-02:00",
		"CompressedSize": "1009333",
		"BeginTime": "2017-12-07T06:03:15.5778243-02:00",
		"FullSize": "1015786"
	},
	{
		"Compression": "zip",
		"Quality": 11,
		"Size": "01MB",
		"Type": "MP3",
		"EndTime": "2017-12-07T06:03:19.0244941-02:00",
		"CompressedSize": "1009333",
		"BeginTime": "2017-12-07T06:03:17.7398048-02:00",
		"FullSize": "1015786"
	},
	{
		"Compression": "tgz",
		"Quality": 5,
		"Size": "01MB",
		"Type": "MP3",
		"EndTime": "2017-12-07T06:03:21.1626223-02:00",
		"CompressedSize": "1006814",
		"BeginTime": "2017-12-07T06:03:19.9181324-02:00",
		"FullSize": "1015786"
	},
	{
		"Compression": "tgz",
		"Quality": 11,
		"Size": "01MB",
		"Type": "MP3",
		"EndTime": "2017-12-07T06:03:23.2576734-02:00",
		"CompressedSize": "1006815",
		"BeginTime": "2017-12-07T06:03:21.9911132-02:00",
		"FullSize": "1015786"
	},
	{
		"Compression": "zip",
		"Quality": 5,
		"Size": "30MB",
		"Type": "MP3",
		"EndTime": "2017-12-07T06:03:27.9936191-02:00",
		"CompressedSize": "31063110",
		"BeginTime": "2017-12-07T06:03:24.2210632-02:00",
		"FullSize": "31172089"
	},
	{
		"Compression": "zip",
		"Quality": 11,
		"Size": "30MB",
		"Type": "MP3",
		"EndTime": "2017-12-07T06:03:33.0877999-02:00",
		"CompressedSize": "31063110",
		"BeginTime": "2017-12-07T06:03:28.9971412-02:00",
		"FullSize": "31172089"
	},
	{
		"Compression": "tgz",
		"Quality": 5,
		"Size": "30MB",
		"Type": "MP3",
		"EndTime": "2017-12-07T06:03:37.8095245-02:00",
		"CompressedSize": "31029714",
		"BeginTime": "2017-12-07T06:03:34.1427774-02:00",
		"FullSize": "31172089"
	},
	{
		"Compression": "tgz",
		"Quality": 11,
		"Size": "30MB",
		"Type": "MP3",
		"EndTime": "2017-12-07T06:03:42.2012816-02:00",
		"CompressedSize": "31029696",
		"BeginTime": "2017-12-07T06:03:38.6094576-02:00",
		"FullSize": "31172089"
	},
	{
		"Compression": "zip",
		"Quality": 5,
		"Size": "01MB",
		"Type": "MP4",
		"EndTime": "2017-12-07T06:03:44.4829909-02:00",
		"CompressedSize": "1054756",
		"BeginTime": "2017-12-07T06:03:43.1492505-02:00",
		"FullSize": "1055736"
	},
	{
		"Compression": "zip",
		"Quality": 11,
		"Size": "01MB",
		"Type": "MP4",
		"EndTime": "2017-12-07T06:03:46.6286933-02:00",
		"CompressedSize": "1054756",
		"BeginTime": "2017-12-07T06:03:45.374535-02:00",
		"FullSize": "1055736"
	},
	{
		"Compression": "tgz",
		"Quality": 5,
		"Size": "01MB",
		"Type": "MP4",
		"EndTime": "2017-12-07T06:03:48.8234497-02:00",
		"CompressedSize": "1054517",
		"BeginTime": "2017-12-07T06:03:47.5377605-02:00",
		"FullSize": "1055736"
	},
	{
		"Compression": "tgz",
		"Quality": 11,
		"Size": "01MB",
		"Type": "MP4",
		"EndTime": "2017-12-07T06:03:50.8735939-02:00",
		"CompressedSize": "1054517",
		"BeginTime": "2017-12-07T06:03:49.6255358-02:00",
		"FullSize": "1055736"
	},
	{
		"Compression": "zip",
		"Quality": 5,
		"Size": "30MB",
		"Type": "MP4",
		"EndTime": "2017-12-07T06:03:55.3344386-02:00",
		"CompressedSize": "31450525",
		"BeginTime": "2017-12-07T06:03:51.7777262-02:00",
		"FullSize": "31491130"
	},
	{
		"Compression": "zip",
		"Quality": 11,
		"Size": "30MB",
		"Type": "MP4",
		"EndTime": "2017-12-07T06:03:59.7910682-02:00",
		"CompressedSize": "31450525",
		"BeginTime": "2017-12-07T06:03:56.2092109-02:00",
		"FullSize": "31491130"
	},
	{
		"Compression": "tgz",
		"Quality": 5,
		"Size": "30MB",
		"Type": "MP4",
		"EndTime": "2017-12-07T06:04:06.4596001-02:00",
		"CompressedSize": "31447646",
		"BeginTime": "2017-12-07T06:04:01.4305142-02:00",
		"FullSize": "31491130"
	},
	{
		"Compression": "tgz",
		"Quality": 11,
		"Size": "30MB",
		"Type": "MP4",
		"EndTime": "2017-12-07T06:04:11.5963804-02:00",
		"CompressedSize": "31447649",
		"BeginTime": "2017-12-07T06:04:07.4454695-02:00",
		"FullSize": "31491130"
	}
]